Workbook

Sheet Assumptions
A1: Kesho Capital — Data Notes and Assumptions
A3: Reporting currency | B3: NGN
A4: FX rate assumption (NGN per USD) | B4: 1550 | C4: Illustrative snapshot rate for this exercise. Production should source a live rate per valuation date, not a hardcoded one.
A5: As-of date for this data | B5: 2025-05-01
A7: Methodology notes
A8: • Kesho's ownership % in each fund is estimated as committed capital ÷ total fund size, taken from the LPA or GP statement where available. This is an approximation — actual economic share can differ with side letters or a preferred-return waterfall. Confirm against Kesho's capital account statements where they exist.
A9: • Capital call figures on the CashFlowEvents tab represent Kesho's own call notices — already Kesho's pro-rata share — net of the management fees and operating expenses each notice bundles in.
A10: • Data-quality flags (ZeroOrPlaceholder, MissingMetrics) are excluded from performance ratios and shown as “Needs Review” rather than a misleading number.
A11: • Craftbyte Software and Zolapay were divested and have been reclassified from Active to Exited here, with illustrative exit dates and proceeds, since Kesho's own source tracker had not yet been updated at the time of the onboarding calls.
A12: • Kola Advisory is listed as Pipeline (under consideration), not an active commitment, and is excluded from all portfolio totals.

Sheet DirectPositions
A1: position_id | B1: name | C1: sector | D1: basis | E1: currency | F1: cost_or_stake_usd | G1: current_fair_value_usd | H1: co_investors | I1: tradable | J1: status
A2: DP-01 | B2: Greenline Rail SPV | C2: Infrastructure | D2: Cost | E2: USD | F2: 12000000 | G2: 12000000 | H2: Pension fund; strategic industrial partner | I2: No | J2: Active
A3: DP-02 | B3: Anka Manufacturing Holding | C3: Industrials | D3: Revenue multiple | E3: USD | F3: 6000000 | G3: 7200000 | I3: No | J3: Active
A4: DP-03 | B4: Coastal Free-Zone Asset | C4: Real assets | D4: Mark-to-market | E4: USD | F4: 4000000 | G4: 3750000 | I4: No | J4: Active
A5: Note: Coastal Free-Zone Asset is an inherited listed stake Kesho cannot trade; held for legacy reasons.

Sheet FundCommitments
A1: position_id | B1: manager_name | C1: currency | D1: committed_amount | E1: called_to_date | F1: fund_total_committed_size | G1: fund_reported_nav | H1: kesho_ownership_pct | I1: kesho_share_of_nav | J1: status
A2: FC-01 | B2: Marara Capital (Fund II) | C2: USD | D2: 10000000 | E2: 6000000 | F2: 150000000 | G2: 172500000 | H2: =D2/F2 -> 0.066666667 | I2: =H2*G2 -> 11500000 | J2: Active
A3: FC-02 | B3: Subira Ventures | C3: USD | D3: 5000000 | E3: 2000000 | F3: 60000000 | G3: 50000000 | H3: =D3/F3 -> 0.083333333 | I3: =H3*G3 -> 4166666.7 | J3: Active
A4: FC-03 | B4: Harmattan Infrastructure Partners | C4: USD | D4: 8000000 | E4: 8000000 | F4: 200000000 | G4: 230000000 | H4: =D4/F4 -> 0.04 | I4: =H4*G4 -> 9200000 | J4: Active
A5: FC-04 | B5: Kanuri Capital | C5: USD | D5: 6000000 | E5: 3000000 | F5: 80000000 | G5: 70000000 | H5: =D5/F5 -> 0.075 | I5: =H5*G5 -> 5250000 | J5: Active
A6: FC-05 | B6: Kola Advisory | C6: USD | D6: 0 | E6: 0 | F6: 0 | G6: 0 | H6: 0 | I6: 0 | J6: Pipeline
A8: Note: kesho_ownership_pct and kesho_share_of_nav are calculated fields (see Assumptions tab for methodology and caveats).

Sheet CashFlowEvents
A1: event_id | B1: position_id | C1: event_date | D1: event_type | E1: gross_amount | F1: fee_component | G1: opex_component | H1: net_invested_capital | I1: distribution_amount
A2: CF-01 | B2: FC-01 | C2: 2022-03-15 | D2: Call | E2: 2500000 | F2: 150000 | G2: 20000 | H2: =IF(D2="Call",E2-F2-G2,0) -> 2330000 | I2: =IF(D2="Distribution",E2,0) -> 0
A3: CF-02 | B3: FC-01 | C3: 2022-11-01 | D3: Call | E3: 2000000 | F3: 120000 | G3: 10000 | H3: =IF(D3="Call",E3-F3-G3,0) -> 1870000 | I3: =IF(D3="Distribution",E3,0) -> 0
A4: CF-03 | B4: FC-01 | C4: 2023-08-10 | D4: Call | E4: 1500000 | F4: 90000 | G4: 10000 | H4: =IF(D4="Call",E4-F4-G4,0) -> 1400000 | I4: =IF(D4="Distribution",E4,0) -> 0
A5: CF-04 | B5: FC-01 | C5: 2023-12-01 | D5: Distribution | E5: 800000 | F5: 0 | G5: 0 | H5: =IF(D5="Call",E5-F5-G5,0) -> 0 | I5: =IF(D5="Distribution",E5,0) -> 800000
A6: CF-05 | B6: FC-02 | C6: 2023-01-20 | D6: Call | E6: 1200000 | F6: 80000 | G6: 10000 | H6: =IF(D6="Call",E6-F6-G6,0) -> 1110000 | I6: =IF(D6="Distribution",E6,0) -> 0
A7: CF-06 | B7: FC-02 | C7: 2023-09-05 | D7: Call | E7: 800000 | F7: 50000 | G7: 10000 | H7: =IF(D7="Call",E7-F7-G7,0) -> 740000 | I7: =IF(D7="Distribution",E7,0) -> 0
A8: CF-07 | B8: FC-03 | C8: 2019-06-01 | D8: Call | E8: 2500000 | F8: 200000 | G8: 30000 | H8: =IF(D8="Call",E8-F8-G8,0) -> 2270000 | I8: =IF(D8="Distribution",E8,0) -> 0
A9: CF-08 | B9: FC-03 | C9: 2020-05-15 | D9: Call | E9: 2500000 | F9: 180000 | G9: 20000 | H9: =IF(D9="Call",E9-F9-G9,0) -> 2300000 | I9: =IF(D9="Distribution",E9,0) -> 0
A10: CF-09 | B10: FC-03 | C10: 2021-04-10 | D10: Call | E10: 2000000 | F10: 140000 | G10: 20000 | H10: =IF(D10="Call",E10-F10-G10,0) -> 1840000 | I10: =IF(D10="Distribution",E10,0) -> 0
A11: CF-10 | B11: FC-03 | C11: 2022-03-01 | D11: Call | E11: 1000000 | F11: 70000 | G11: 10000 | H11: =IF(D11="Call",E11-F11-G11,0) -> 920000 | I11: =IF(D11="Distribution",E11,0) -> 0
A12: CF-11 | B12: FC-03 | C12: 2022-12-01 | D12: Distribution | E12: 600000 | F12: 0 | G12: 0 | H12: =IF(D12="Call",E12-F12-G12,0) -> 0 | I12: =IF(D12="Distribution",E12,0) -> 600000
A13: CF-12 | B13: FC-03 | C13: 2023-12-01 | D13: Distribution | E13: 650000 | F13: 0 | G13: 0 | H13: =IF(D13="Call",E13-F13-G13,0) -> 0 | I13: =IF(D13="Distribution",E13,0) -> 650000
... A15: CF-14 | B15: FC-04 | C15: 2023-06-15 | D15: Call | E15: 1200000 | F15: 80000 | G15: 10000 | H15: =IF(D15="Call",E15-F15-G15,0) -> 1110000 | I15: =IF(D15="Distribution",E15,0) -> 0
A17: Note: gross_amount, fee_component and opex_component reflect Kesho's own call notices, not fund-level totals — this is the schedule referenced in the reporting note to isolate Kesho's actual invested capital.

Sheet ImpactHoldings
A1: position_id | B1: portfolio_company | C1: cost_ngn | D1: fair_value_ngn | E1: status | F1: exit_date | G1: exit_proceeds_ngn | H1: data_quality_flag | I1: moic
A2: IH-01 | B2: Harvestbridge Foods | C2: 1200000000 | D2: 1600000000 | E2: Active | H2: Clean | I2: =IF(E2="Exited",IFERROR(G2/C2,"Needs Review"),IF(H2="Clean",IFERROR(D2/C2,"Needs Review"),"Needs Review")) -> 1.3333333
A3: IH-02 | B3: Craftbyte Software | C3: 800000000 | E3: Exited | F3: 2025-02-20 | G3: 1100000000 | H3: Clean | I3: =IF(E3="Exited",IFERROR(G3/C3,"Needs Review"),IF(H3="Clean",IFERROR(D3/C3,"Needs Review"),"Needs Review")) -> 1.375
A4: IH-03 | B4: Zolapay | C4: 500000000 | E4: Exited | F4: 2025-01-10 | G4: 300000000 | H4: Clean | I4: =IF(E4="Exited",IFERROR(G4/C4,"Needs Review"),IF(H4="Clean",IFERROR(D4/C4,"Needs Review"),"Needs Review")) -> 0.6
A5: IH-04 | B5: Greenwatt Utilities | C5: 900000000 | D5: 0 | E5: Active | H5: ZeroOrPlaceholder | I5: =IF(E5="Exited",IFERROR(G5/C5,"Needs Review"),IF(H5="Clean",IFERROR(D5/C5,"Needs Review"),"Needs Review")) -> Needs Review
A6: IH-05 | B6: SkillSprout Africa | C6: 600000000 | E6: Active | H6: MissingMetrics | I6: =IF(E6="Exited",IFERROR(G6/C6,"Needs Review"),IF(H6="Clean",IFERROR(D6/C6,"Needs Review"),"Needs Review")) -> Needs Review
A8: Note: Greenwatt (zero/placeholder value) and SkillSprout (missing fair value) are flagged Needs Review, not silently included in performance ratios.

Sheet PortfolioSummary
A1: Kesho Capital — Portfolio Summary (Active positions only)
A2: As of Assumptions!B5 — all figures converted to NGN at the FX rate on the Assumptions tab
A4: 1. Direct Positions
A5: Total cost (USD) | B5: =SUMIFS(DirectPositions!F2:F4,DirectPositions!J2:J4,"Active") -> 22000000
A6: Total fair value (USD) | B6: =SUMIFS(DirectPositions!G2:G4,DirectPositions!J2:J4,"Active") -> 22950000
A7: Total cost (NGN) | B7: =B5*Assumptions!$B$4 -> 34100000000
A8: Total fair value (NGN) | B8: =B6*Assumptions!$B$4 -> 35572500000
A10: 2. Fund-of-Funds Commitments
A11: Total Kesho net invested capital, all funds (USD) | B11: =SUM(CashFlowEvents!H2:H15) -> 17550000
A12: Total Kesho distributions received (USD) | B12: =SUM(CashFlowEvents!I2:I15) -> 2050000
A13: Total Kesho current share of NAV (USD) | B13: =SUMIFS(FundCommitments!I2:I6,FundCommitments!J2:J6,"Active") -> 30116667
A14: Total net invested capital (NGN) | B14: =B11*Assumptions!$B$4 -> 27202500000
A15: Total current share of NAV (NGN) | B15: =B13*Assumptions!$B$4 -> 4.6680833e+10
A16: Portfolio-level MOIC (funds only) | B16: =IFERROR((B12+B13)/B11,"Needs Review") -> 1.8328585
A18: 3. Wholly-Owned Impact Fund
A19: Total cost (NGN) | B19: =SUMIFS(ImpactHoldings!C2:C6,ImpactHoldings!E2:E6,"Active") -> 2700000000
A20: Total fair value (NGN) — excludes flagged positions valued at 0/blank | B20: =SUMIFS(ImpactHoldings!D2:D6,ImpactHoldings!E2:E6,"Active") -> 1600000000
A21: Active positions flagged Needs Review | B21: =COUNTIFS(ImpactHoldings!E2:E6,"Active",ImpactHoldings!H2:H6,"<>Clean") -> 2
A23: 4. Total Portfolio (NGN, Active positions, Kesho's actual share)
A24: Total cost / invested capital | B24: =B7+B14+B19 -> 64002500000
A25: Total fair value | B25: =B8+B15+B20 -> 8.3853333e+10
A27: 5. Recently Exited
A28: Company | B28: Exit date | C28: Cost (NGN) | D28: Exit proceeds (NGN) | E28: Realized MOIC
A29: =ImpactHoldings!B3 -> Craftbyte Software | B29: =ImpactHoldings!F3 -> 2025-02-20 | C29: =ImpactHoldings!C3 -> 800000000 | D29: =ImpactHoldings!G3 -> 1100000000 | E29: =ImpactHoldings!I3 -> 1.375
A30: =ImpactHoldings!B4 -> Zolapay | B30: =ImpactHoldings!F4 -> 2025-01-10 | C30: =ImpactHoldings!C4 -> 500000000 | D30: =ImpactHoldings!G4 -> 300000000 | E30: =ImpactHoldings!I4 -> 0.6
